odoo10_addon_mrp_production_note-10.0.1.0.0-py2.7-nspkg.pth
odoo10_addon_mrp_production_note-10.0.1.0.0.dist-info/top_level.txt
odoo10_addon_mrp_production_note-10.0.1.0.0.dist-info/WHEEL
odoo10_addon_mrp_production_note-10.0.1.0.0.dist-info/RECORD
odoo10_addon_mrp_production_note-10.0.1.0.0.dist-info/metadata.json
odoo10_addon_mrp_production_note-10.0.1.0.0.dist-info/DESCRIPTION.rst
odoo10_addon_mrp_production_note-10.0.1.0.0.dist-info/METADATA
odoo10_addon_mrp_production_note-10.0.1.0.0.dist-info/namespace_packages.txt
odoo/addons/mrp_production_note/__manifest__.py
odoo/addons/mrp_production_note/__init__.py
odoo/addons/mrp_production_note/README.rst
odoo/addons/mrp_production_note/models/mrp_production.py
odoo/addons/mrp_production_note/models/__init__.py
odoo/addons/mrp_production_note/i18n/zh_CN.po
odoo/addons/mrp_production_note/i18n/es.po
odoo/addons/mrp_production_note/i18n/mrp_production_notes.pot
odoo/addons/mrp_production_note/i18n/de.po
odoo/addons/mrp_production_note/i18n/pt_BR.po
odoo/addons/mrp_production_note/views/mrp_production_view.xml
